pixy/__init__.py
pixy/colours/__init__.py
pixy/colours/background.py
pixy/colours/constants.py
pixy/colours/foreground.py
pixy/decorators.py
pixy/escape_sequence.py
pixy/extended_colour.py
pixy/font.py
pixy/helpers.py
pixy/pring.py
pixy/true_colour.py
pixy-1.0.3.dist-info/LICENSE
pixy-1.0.3.dist-info/WHEEL
pixy-1.0.3.dist-info/METADATA
pixy-1.0.3.dist-info/RECORD
