Metadata-Version: 2.1
Name: pixy
Version: 1.0.3
Summary: Add colour and style to terminal text
Home-page: https://github.com/kiancross/pixy
License: MIT
Keywords: colour,color,terminal,style,text
Author: Kian Cross
Author-email: kian@kiancross.co.uk
Maintainer: Kian Cross
Maintainer-email: kian@kiancross.co.uk
Requires-Python: >=3.6,<4.0
Classifier: Development Status :: 5 - Production/Stable
Classifier: Environment :: Console
Classifier: Intended Audience :: Developers
Classifier: License :: OSI Approved :: MIT License
Classifier: Operating System :: OS Independent
Classifier: Programming Language :: Python :: 3
Classifier: Programming Language :: Python :: 3.6
Classifier: Programming Language :: Python :: 3.7
Classifier: Programming Language :: Python :: 3.8
Classifier: Programming Language :: Python :: 3.9
Classifier: Topic :: Software Development :: Libraries :: Python Modules
Project-URL: Documentation, https://github.com/kiancross/pixy
Project-URL: Repository, https://github.com/kiancross/pixy
